{
  "_meta": {
    "sources": [
      "loopback/common/models",
      "loopback/server/models",
      "../common/models"
    ]
  },
  "AminoAccessToken": {
    "dataSource": "amino_admin_pg",
    "public": true
  },
  "AminoUser": {
    "dataSource": "amino_admin_pg",
    "public": true
  },
  "AminoRole": {
    "dataSource": "amino_admin_pg",
    "public": true
  },
  "AminoPostalMessage": {
    "dataSource": "amino_admin_pg",
    "public": true
  },
  "AminoRoleMapping": {
    "dataSource": "amino_admin_pg",
    "public": true
  },
  "ACL": {
    "dataSource": "amino_admin_pg",
    "public": true
  },
  "Backdoor": {
    "dataSource": "amino_admin_pg",
    "public": true
  },
  "UploadedFile": {
    "dataSource": "amino_admin_pg",
    "public": true
  },
  "RemoteLog": {
    "dataSource": "amino_admin_pg",
    "public": true
  },
  "WebSocket": {
    "dataSource": "amino_admin_pg",
    "public": true
  },
  "LogEntry": {
    "dataSource": "amino_admin_pg",
    "public": true
  },
  "DataSet": {
    "dataSource": "amino_admin_pg",
    "public": true
  },
  "AminoFile": {
    "dataSource": "amino_admin_pg",
    "public": true
  },
  "MetadataInfoCatalog": {
    "dataSource": "amino_admin_pg",
    "public": true
  },
  "MetadataInfoCatalogPedigree": {
    "dataSource": "amino_admin_pg",
    "public": true
  },
  "Elasticsearch": {
    "dataSource": "amino_admin_pg",
    "public": true
  },
  "SparkApplication": {
    "dataSource": "amino_admin_pg",
    "public": true
  },
  "SparkJob": {
    "dataSource": "amino_admin_pg",
    "public": true
  },
  "SparkPedigree": {
    "dataSource": "amino_admin_pg",
    "public": true
  },
  "LoopbackModel": {
    "dataSource": "amino_admin_pg",
    "public": true
  },
  "ServerService": {
    "dataSource": "amino_admin_pg",
    "public": true
  }
}

